masakhanePreprocessor/__init__.py
masakhanePreprocessor/langs.py
masakhanePreprocessor/languages.json
masakhanePreprocessor/preprocess.py
masakhanePreprocessor/rules/fon.json
masakhanePreprocessor/rules/ig.json
masakhanePreprocessor/rules/yo.json
masakhanePreprocessor-0.0.6.dist-info/METADATA
masakhanePreprocessor-0.0.6.dist-info/WHEEL
masakhanePreprocessor-0.0.6.dist-info/top_level.txt
masakhanePreprocessor-0.0.6.dist-info/RECORD
