Metadata-Version: 2.1
Name: masakhanePreprocessor
Version: 0.0.6
Summary: masakhanePreprocessor is an effective language-first preprocessing tool for African languages
Home-page: https://github.com/masakhane-io/masakhane-preprocessing
Author: Masakhane Contributors: https://github.com/masakhane-io/masakhane-preprocessor/graphs/contributors
Author-email: masakhane-nlp@googlegroups.com
License: Apache License
Project-URL: Documentation, https://github.com/masakhane-io/masakhane-preprocessing
Project-URL: Source, https://github.com/masakhane-io/masakhane-preprocessing
Project-URL: Tracker, https://github.com/masakhane-io/masakhane-preprocessing/issues
Platform: UNKNOWN
Requires-Python: >=3.7
Requires-Dist: clean-text
Requires-Dist: langcodes
